infery.pyi
infery.cpython-37m-x86_64-linux-gnu.so
tests.pyi
tests.cpython-37m-x86_64-linux-gnu.so
infery_gpu-3.9.0.dist-info/top_level.txt
infery_gpu-3.9.0.dist-info/RECORD
infery_gpu-3.9.0.dist-info/METADATA
infery_gpu-3.9.0.dist-info/WHEEL
infery_gpu-3.9.0.dist-info/LICENSE
